README.md
setup.py
greendeck_rabbitmq/__init__.py
greendeck_rabbitmq.egg-info/PKG-INFO
greendeck_rabbitmq.egg-info/SOURCES.txt
greendeck_rabbitmq.egg-info/dependency_links.txt
greendeck_rabbitmq.egg-info/not-zip-safe
greendeck_rabbitmq.egg-info/requires.txt
greendeck_rabbitmq.egg-info/top_level.txt
greendeck_rabbitmq/src/__init__.py
greendeck_rabbitmq/src/rabbitmq/__init__.py
greendeck_rabbitmq/src/rabbitmq/rabbitmq.py