Metadata-Version: 2.1
Name: greendeck-rabbitmq
Version: 1.0.11
Summary: Greendeck rabbitmq package
Home-page: https://github.com/IIITian-Chandan/greendeck-rabbitmq.git
Author: chandan mishra
Author-email: chandan.mishra@greendeck.co
License: UNKNOWN
Platform: UNKNOWN
Classifier: Programming Language :: Python :: 3
Classifier: License :: OSI Approved :: MIT License
Classifier: Operating System :: OS Independent
